nonebot_plugin_todo_nlp/__init__.py
nonebot_plugin_todo_nlp/config.py
nonebot_plugin_todo_nlp/nlp_util.py
nonebot_plugin_todo_nlp/templates/css/style.css
nonebot_plugin_todo_nlp/templates/template.html
nonebot_plugin_todo_nlp/todo.py
nonebot_plugin_todo_nlp/todo_manage.py
nonebot_plugin_todo_nlp-0.1.9.dist-info/LICENSE
nonebot_plugin_todo_nlp-0.1.9.dist-info/METADATA
nonebot_plugin_todo_nlp-0.1.9.dist-info/WHEEL
nonebot_plugin_todo_nlp-0.1.9.dist-info/RECORD
